fable/__init__.py
fable/_util.py
fable/fable.py
fable/test_fable.py
fable_circuits-1.0.2.dist-info/METADATA
fable_circuits-1.0.2.dist-info/WHEEL
fable_circuits-1.0.2.dist-info/top_level.txt
fable_circuits-1.0.2.dist-info/RECORD
