Metadata-Version: 2.1
Name: fable-circuits
Version: 1.0.2
Summary: Fast Approximate Block Encoding Circuits
Home-page: https://github.com/QuantumComputingLab/fable
Author: Daan Camps
Author-email: daancamps@gmail.com
License: : BSD
Requires-Python: >=3.6
Requires-Dist: qiskit>=0.19.1
Requires-Dist: numpy>=1.20.3
